{
  "swagger" : "2.0",
  "info" : {
    "description" : "pr1 Service REST API - Complete",
    "version" : "2025-11-04T01:11:45Z",
    "title" : "pr1-rest-api"
  },
  "host" : "ausack90jb.execute-api.us-east-1.amazonaws.com",
  "basePath" : "/prod",
  "schemes" : [ "https" ],
  "paths" : {
    "/admin/dashboard" : {
      "get" : {
        "responses" : {
          "200" : {
            "description" : "200 response",
            "headers" : {
              "Access-Control-Allow-Origin" : {
                "type" : "string"
              },
              "Access-Control-Allow-Methods" : {
                "type" : "string"
              },
              "Access-Control-Allow-Credentials" : {
                "type" : "string"
              },
              "Access-Control-Allow-Headers" : {
                "type" : "string"
              }
            }
          },
          "500" : {
            "description" : "500 response",
            "headers" : {
              "Access-Control-Allow-Origin" : {
                "type" : "string"
              }
            }
          }
        }
      },
      "put" : {
        "responses" : {
          "200" : {
            "description" : "200 response",
            "headers" : {
              "Access-Control-Allow-Origin" : {
                "type" : "string"
              },
              "Access-Control-Allow-Methods" : {
                "type" : "string"
              },
              "Access-Control-Allow-Credentials" : {
                "type" : "string"
              },
              "Access-Control-Allow-Headers" : {
                "type" : "string"
              }
            }
          },
          "500" : {
            "description" : "500 response",
            "headers" : {
              "Access-Control-Allow-Origin" : {
                "type" : "string"
              }
            }
          }
        }
      },
      "options" : {
        "consumes" : [ "application/json" ],
        "responses" : {
          "200" : {
            "description" : "200 response",
            "headers" : {
              "Access-Control-Allow-Origin" : {
                "type" : "string"
              },
              "Access-Control-Allow-Methods" : {
                "type" : "string"
              },
              "Access-Control-Allow-Credentials" : {
                "type" : "string"
              },
              "Access-Control-Allow-Headers" : {
                "type" : "string"
              }
            }
          }
        }
      }
    },
    "/admin/usage" : {
      "get" : {
        "responses" : {
          "200" : {
            "description" : "200 response",
            "headers" : {
              "Access-Control-Allow-Origin" : {
                "type" : "string"
              },
              "Access-Control-Allow-Methods" : {
                "type" : "string"
              },
              "Access-Control-Allow-Credentials" : {
                "type" : "string"
              },
              "Access-Control-Allow-Headers" : {
                "type" : "string"
              }
            }
          },
          "500" : {
            "description" : "500 response",
            "headers" : {
              "Access-Control-Allow-Origin" : {
                "type" : "string"
              }
            }
          }
        }
      },
      "put" : {
        "responses" : {
          "200" : {
            "description" : "200 response",
            "headers" : {
              "Access-Control-Allow-Origin" : {
                "type" : "string"
              },
              "Access-Control-Allow-Methods" : {
                "type" : "string"
              },
              "Access-Control-Allow-Credentials" : {
                "type" : "string"
              },
              "Access-Control-Allow-Headers" : {
                "type" : "string"
              }
            }
          },
          "500" : {
            "description" : "500 response",
            "headers" : {
              "Access-Control-Allow-Origin" : {
                "type" : "string"
              }
            }
          }
        }
      },
      "options" : {
        "consumes" : [ "application/json" ],
        "responses" : {
          "200" : {
            "description" : "200 response",
            "headers" : {
              "Access-Control-Allow-Origin" : {
                "type" : "string"
              },
              "Access-Control-Allow-Methods" : {
                "type" : "string"
              },
              "Access-Control-Allow-Credentials" : {
                "type" : "string"
              },
              "Access-Control-Allow-Headers" : {
                "type" : "string"
              }
            }
          }
        }
      }
    },
    "/admin/users" : {
      "get" : {
        "responses" : {
          "200" : {
            "description" : "200 response",
            "headers" : {
              "Access-Control-Allow-Origin" : {
                "type" : "string"
              },
              "Access-Control-Allow-Methods" : {
                "type" : "string"
              },
              "Access-Control-Allow-Credentials" : {
                "type" : "string"
              },
              "Access-Control-Allow-Headers" : {
                "type" : "string"
              }
            }
          },
          "500" : {
            "description" : "500 response",
            "headers" : {
              "Access-Control-Allow-Origin" : {
                "type" : "string"
              }
            }
          }
        }
      },
      "put" : {
        "responses" : {
          "200" : {
            "description" : "200 response",
            "headers" : {
              "Access-Control-Allow-Origin" : {
                "type" : "string"
              },
              "Access-Control-Allow-Methods" : {
                "type" : "string"
              },
              "Access-Control-Allow-Credentials" : {
                "type" : "string"
              },
              "Access-Control-Allow-Headers" : {
                "type" : "string"
              }
            }
          },
          "500" : {
            "description" : "500 response",
            "headers" : {
              "Access-Control-Allow-Origin" : {
                "type" : "string"
              }
            }
          }
        }
      },
      "options" : {
        "consumes" : [ "application/json" ],
        "responses" : {
          "200" : {
            "description" : "200 response",
            "headers" : {
              "Access-Control-Allow-Origin" : {
                "type" : "string"
              },
              "Access-Control-Allow-Methods" : {
                "type" : "string"
              },
              "Access-Control-Allow-Credentials" : {
                "type" : "string"
              },
              "Access-Control-Allow-Headers" : {
                "type" : "string"
              }
            }
          }
        }
      }
    },
    "/conversations" : {
      "get" : {
        "responses" : {
          "200" : {
            "description" : "200 response",
            "headers" : {
              "Access-Control-Allow-Origin" : {
                "type" : "string"
              },
              "Access-Control-Allow-Methods" : {
                "type" : "string"
              },
              "Access-Control-Allow-Credentials" : {
                "type" : "string"
              },
              "Access-Control-Allow-Headers" : {
                "type" : "string"
              }
            }
          },
          "500" : {
            "description" : "500 response",
            "headers" : {
              "Access-Control-Allow-Origin" : {
                "type" : "string"
              }
            }
          }
        }
      },
      "post" : {
        "responses" : {
          "200" : {
            "description" : "200 response",
            "headers" : {
              "Access-Control-Allow-Origin" : {
                "type" : "string"
              },
              "Access-Control-Allow-Methods" : {
                "type" : "string"
              },
              "Access-Control-Allow-Credentials" : {
                "type" : "string"
              },
              "Access-Control-Allow-Headers" : {
                "type" : "string"
              }
            }
          },
          "500" : {
            "description" : "500 response",
            "headers" : {
              "Access-Control-Allow-Origin" : {
                "type" : "string"
              }
            }
          }
        }
      },
      "put" : {
        "responses" : {
          "200" : {
            "description" : "200 response",
            "headers" : {
              "Access-Control-Allow-Origin" : {
                "type" : "string"
              },
              "Access-Control-Allow-Methods" : {
                "type" : "string"
              },
              "Access-Control-Allow-Credentials" : {
                "type" : "string"
              },
              "Access-Control-Allow-Headers" : {
                "type" : "string"
              }
            }
          },
          "500" : {
            "description" : "500 response",
            "headers" : {
              "Access-Control-Allow-Origin" : {
                "type" : "string"
              }
            }
          }
        }
      },
      "options" : {
        "consumes" : [ "application/json" ],
        "responses" : {
          "200" : {
            "description" : "200 response",
            "headers" : {
              "Access-Control-Allow-Origin" : {
                "type" : "string"
              },
              "Access-Control-Allow-Methods" : {
                "type" : "string"
              },
              "Access-Control-Allow-Credentials" : {
                "type" : "string"
              },
              "Access-Control-Allow-Headers" : {
                "type" : "string"
              }
            }
          }
        }
      }
    },
    "/conversations/{conversationId}" : {
      "get" : {
        "parameters" : [ {
          "name" : "conversationId",
          "in" : "path",
          "required" : true,
          "type" : "string"
        } ],
        "responses" : {
          "200" : {
            "description" : "200 response",
            "headers" : {
              "Access-Control-Allow-Origin" : {
                "type" : "string"
              },
              "Access-Control-Allow-Methods" : {
                "type" : "string"
              },
              "Access-Control-Allow-Credentials" : {
                "type" : "string"
              },
              "Access-Control-Allow-Headers" : {
                "type" : "string"
              }
            }
          },
          "500" : {
            "description" : "500 response",
            "headers" : {
              "Access-Control-Allow-Origin" : {
                "type" : "string"
              }
            }
          }
        }
      },
      "put" : {
        "parameters" : [ {
          "name" : "conversationId",
          "in" : "path",
          "required" : true,
          "type" : "string"
        } ],
        "responses" : {
          "200" : {
            "description" : "200 response",
            "headers" : {
              "Access-Control-Allow-Origin" : {
                "type" : "string"
              },
              "Access-Control-Allow-Methods" : {
                "type" : "string"
              },
              "Access-Control-Allow-Credentials" : {
                "type" : "string"
              },
              "Access-Control-Allow-Headers" : {
                "type" : "string"
              }
            }
          },
          "500" : {
            "description" : "500 response",
            "headers" : {
              "Access-Control-Allow-Origin" : {
                "type" : "string"
              }
            }
          }
        }
      },
      "delete" : {
        "parameters" : [ {
          "name" : "conversationId",
          "in" : "path",
          "required" : true,
          "type" : "string"
        } ],
        "responses" : {
          "200" : {
            "description" : "200 response",
            "headers" : {
              "Access-Control-Allow-Origin" : {
                "type" : "string"
              },
              "Access-Control-Allow-Methods" : {
                "type" : "string"
              },
              "Access-Control-Allow-Credentials" : {
                "type" : "string"
              },
              "Access-Control-Allow-Headers" : {
                "type" : "string"
              }
            }
          },
          "500" : {
            "description" : "500 response",
            "headers" : {
              "Access-Control-Allow-Origin" : {
                "type" : "string"
              }
            }
          }
        }
      },
      "options" : {
        "consumes" : [ "application/json" ],
        "parameters" : [ {
          "name" : "conversationId",
          "in" : "path",
          "required" : true,
          "type" : "string"
        } ],
        "responses" : {
          "200" : {
            "description" : "200 response",
            "headers" : {
              "Access-Control-Allow-Origin" : {
                "type" : "string"
              },
              "Access-Control-Allow-Methods" : {
                "type" : "string"
              },
              "Access-Control-Allow-Credentials" : {
                "type" : "string"
              },
              "Access-Control-Allow-Headers" : {
                "type" : "string"
              }
            }
          }
        }
      },
      "patch" : {
        "parameters" : [ {
          "name" : "conversationId",
          "in" : "path",
          "required" : true,
          "type" : "string"
        } ],
        "responses" : {
          "200" : {
            "description" : "200 response",
            "headers" : {
              "Access-Control-Allow-Origin" : {
                "type" : "string"
              },
              "Access-Control-Allow-Methods" : {
                "type" : "string"
              },
              "Access-Control-Allow-Credentials" : {
                "type" : "string"
              },
              "Access-Control-Allow-Headers" : {
                "type" : "string"
              }
            }
          },
          "500" : {
            "description" : "500 response",
            "headers" : {
              "Access-Control-Allow-Origin" : {
                "type" : "string"
              }
            }
          }
        }
      }
    },
    "/prompts" : {
      "get" : {
        "responses" : {
          "200" : {
            "description" : "200 response",
            "headers" : {
              "Access-Control-Allow-Origin" : {
                "type" : "string"
              },
              "Access-Control-Allow-Methods" : {
                "type" : "string"
              },
              "Access-Control-Allow-Credentials" : {
                "type" : "string"
              },
              "Access-Control-Allow-Headers" : {
                "type" : "string"
              }
            }
          },
          "500" : {
            "description" : "500 response",
            "headers" : {
              "Access-Control-Allow-Origin" : {
                "type" : "string"
              }
            }
          }
        }
      },
      "post" : {
        "responses" : {
          "200" : {
            "description" : "200 response",
            "headers" : {
              "Access-Control-Allow-Origin" : {
                "type" : "string"
              },
              "Access-Control-Allow-Methods" : {
                "type" : "string"
              },
              "Access-Control-Allow-Credentials" : {
                "type" : "string"
              },
              "Access-Control-Allow-Headers" : {
                "type" : "string"
              }
            }
          },
          "500" : {
            "description" : "500 response",
            "headers" : {
              "Access-Control-Allow-Origin" : {
                "type" : "string"
              }
            }
          }
        }
      },
      "options" : {
        "consumes" : [ "application/json" ],
        "responses" : {
          "200" : {
            "description" : "200 response",
            "headers" : {
              "Access-Control-Allow-Origin" : {
                "type" : "string"
              },
              "Access-Control-Allow-Methods" : {
                "type" : "string"
              },
              "Access-Control-Allow-Credentials" : {
                "type" : "string"
              },
              "Access-Control-Allow-Headers" : {
                "type" : "string"
              }
            }
          }
        }
      }
    },
    "/prompts/{promptId}" : {
      "get" : {
        "parameters" : [ {
          "name" : "promptId",
          "in" : "path",
          "required" : true,
          "type" : "string"
        } ],
        "responses" : {
          "200" : {
            "description" : "200 response",
            "headers" : {
              "Access-Control-Allow-Origin" : {
                "type" : "string"
              },
              "Access-Control-Allow-Methods" : {
                "type" : "string"
              },
              "Access-Control-Allow-Credentials" : {
                "type" : "string"
              },
              "Access-Control-Allow-Headers" : {
                "type" : "string"
              }
            }
          },
          "500" : {
            "description" : "500 response",
            "headers" : {
              "Access-Control-Allow-Origin" : {
                "type" : "string"
              }
            }
          }
        }
      },
      "post" : {
        "parameters" : [ {
          "name" : "promptId",
          "in" : "path",
          "required" : true,
          "type" : "string"
        } ],
        "responses" : {
          "200" : {
            "description" : "200 response",
            "headers" : {
              "Access-Control-Allow-Origin" : {
                "type" : "string"
              },
              "Access-Control-Allow-Methods" : {
                "type" : "string"
              },
              "Access-Control-Allow-Credentials" : {
                "type" : "string"
              },
              "Access-Control-Allow-Headers" : {
                "type" : "string"
              }
            }
          },
          "500" : {
            "description" : "500 response",
            "headers" : {
              "Access-Control-Allow-Origin" : {
                "type" : "string"
              }
            }
          }
        }
      },
      "put" : {
        "parameters" : [ {
          "name" : "promptId",
          "in" : "path",
          "required" : true,
          "type" : "string"
        } ],
        "responses" : {
          "200" : {
            "description" : "200 response",
            "headers" : {
              "Access-Control-Allow-Origin" : {
                "type" : "string"
              },
              "Access-Control-Allow-Methods" : {
                "type" : "string"
              },
              "Access-Control-Allow-Credentials" : {
                "type" : "string"
              },
              "Access-Control-Allow-Headers" : {
                "type" : "string"
              }
            }
          },
          "500" : {
            "description" : "500 response",
            "headers" : {
              "Access-Control-Allow-Origin" : {
                "type" : "string"
              }
            }
          }
        }
      },
      "options" : {
        "consumes" : [ "application/json" ],
        "parameters" : [ {
          "name" : "promptId",
          "in" : "path",
          "required" : true,
          "type" : "string"
        } ],
        "responses" : {
          "200" : {
            "description" : "200 response",
            "headers" : {
              "Access-Control-Allow-Origin" : {
                "type" : "string"
              },
              "Access-Control-Allow-Methods" : {
                "type" : "string"
              },
              "Access-Control-Allow-Credentials" : {
                "type" : "string"
              },
              "Access-Control-Allow-Headers" : {
                "type" : "string"
              }
            }
          }
        }
      }
    },
    "/prompts/{promptId}/files" : {
      "get" : {
        "parameters" : [ {
          "name" : "promptId",
          "in" : "path",
          "required" : true,
          "type" : "string"
        } ],
        "responses" : {
          "200" : {
            "description" : "200 response",
            "headers" : {
              "Access-Control-Allow-Origin" : {
                "type" : "string"
              },
              "Access-Control-Allow-Methods" : {
                "type" : "string"
              },
              "Access-Control-Allow-Credentials" : {
                "type" : "string"
              },
              "Access-Control-Allow-Headers" : {
                "type" : "string"
              }
            }
          },
          "500" : {
            "description" : "500 response",
            "headers" : {
              "Access-Control-Allow-Origin" : {
                "type" : "string"
              }
            }
          }
        }
      },
      "post" : {
        "parameters" : [ {
          "name" : "promptId",
          "in" : "path",
          "required" : true,
          "type" : "string"
        } ],
        "responses" : {
          "200" : {
            "description" : "200 response",
            "headers" : {
              "Access-Control-Allow-Origin" : {
                "type" : "string"
              },
              "Access-Control-Allow-Methods" : {
                "type" : "string"
              },
              "Access-Control-Allow-Credentials" : {
                "type" : "string"
              },
              "Access-Control-Allow-Headers" : {
                "type" : "string"
              }
            }
          },
          "500" : {
            "description" : "500 response",
            "headers" : {
              "Access-Control-Allow-Origin" : {
                "type" : "string"
              }
            }
          }
        }
      },
      "options" : {
        "consumes" : [ "application/json" ],
        "parameters" : [ {
          "name" : "promptId",
          "in" : "path",
          "required" : true,
          "type" : "string"
        } ],
        "responses" : {
          "200" : {
            "description" : "200 response",
            "headers" : {
              "Access-Control-Allow-Origin" : {
                "type" : "string"
              },
              "Access-Control-Allow-Methods" : {
                "type" : "string"
              },
              "Access-Control-Allow-Credentials" : {
                "type" : "string"
              },
              "Access-Control-Allow-Headers" : {
                "type" : "string"
              }
            }
          }
        }
      }
    },
    "/prompts/{promptId}/files/{fileId}" : {
      "get" : {
        "parameters" : [ {
          "name" : "promptId",
          "in" : "path",
          "required" : true,
          "type" : "string"
        }, {
          "name" : "fileId",
          "in" : "path",
          "required" : true,
          "type" : "string"
        } ],
        "responses" : {
          "200" : {
            "description" : "200 response",
            "headers" : {
              "Access-Control-Allow-Origin" : {
                "type" : "string"
              },
              "Access-Control-Allow-Methods" : {
                "type" : "string"
              },
              "Access-Control-Allow-Credentials" : {
                "type" : "string"
              },
              "Access-Control-Allow-Headers" : {
                "type" : "string"
              }
            }
          },
          "500" : {
            "description" : "500 response",
            "headers" : {
              "Access-Control-Allow-Origin" : {
                "type" : "string"
              }
            }
          }
        }
      },
      "put" : {
        "parameters" : [ {
          "name" : "promptId",
          "in" : "path",
          "required" : true,
          "type" : "string"
        }, {
          "name" : "fileId",
          "in" : "path",
          "required" : true,
          "type" : "string"
        } ],
        "responses" : {
          "200" : {
            "description" : "200 response",
            "headers" : {
              "Access-Control-Allow-Origin" : {
                "type" : "string"
              },
              "Access-Control-Allow-Methods" : {
                "type" : "string"
              },
              "Access-Control-Allow-Credentials" : {
                "type" : "string"
              },
              "Access-Control-Allow-Headers" : {
                "type" : "string"
              }
            }
          },
          "500" : {
            "description" : "500 response",
            "headers" : {
              "Access-Control-Allow-Origin" : {
                "type" : "string"
              }
            }
          }
        }
      },
      "delete" : {
        "parameters" : [ {
          "name" : "promptId",
          "in" : "path",
          "required" : true,
          "type" : "string"
        }, {
          "name" : "fileId",
          "in" : "path",
          "required" : true,
          "type" : "string"
        } ],
        "responses" : {
          "200" : {
            "description" : "200 response",
            "headers" : {
              "Access-Control-Allow-Origin" : {
                "type" : "string"
              },
              "Access-Control-Allow-Methods" : {
                "type" : "string"
              },
              "Access-Control-Allow-Credentials" : {
                "type" : "string"
              },
              "Access-Control-Allow-Headers" : {
                "type" : "string"
              }
            }
          },
          "500" : {
            "description" : "500 response",
            "headers" : {
              "Access-Control-Allow-Origin" : {
                "type" : "string"
              }
            }
          }
        }
      },
      "options" : {
        "consumes" : [ "application/json" ],
        "parameters" : [ {
          "name" : "promptId",
          "in" : "path",
          "required" : true,
          "type" : "string"
        }, {
          "name" : "fileId",
          "in" : "path",
          "required" : true,
          "type" : "string"
        } ],
        "responses" : {
          "200" : {
            "description" : "200 response",
            "headers" : {
              "Access-Control-Allow-Origin" : {
                "type" : "string"
              },
              "Access-Control-Allow-Methods" : {
                "type" : "string"
              },
              "Access-Control-Allow-Credentials" : {
                "type" : "string"
              },
              "Access-Control-Allow-Headers" : {
                "type" : "string"
              }
            }
          }
        }
      }
    },
    "/usage" : {
      "get" : {
        "responses" : {
          "200" : {
            "description" : "200 response",
            "headers" : {
              "Access-Control-Allow-Origin" : {
                "type" : "string"
              },
              "Access-Control-Allow-Methods" : {
                "type" : "string"
              },
              "Access-Control-Allow-Credentials" : {
                "type" : "string"
              },
              "Access-Control-Allow-Headers" : {
                "type" : "string"
              }
            }
          },
          "500" : {
            "description" : "500 response",
            "headers" : {
              "Access-Control-Allow-Origin" : {
                "type" : "string"
              }
            }
          }
        }
      },
      "post" : {
        "responses" : {
          "200" : {
            "description" : "200 response",
            "headers" : {
              "Access-Control-Allow-Origin" : {
                "type" : "string"
              },
              "Access-Control-Allow-Methods" : {
                "type" : "string"
              },
              "Access-Control-Allow-Credentials" : {
                "type" : "string"
              },
              "Access-Control-Allow-Headers" : {
                "type" : "string"
              }
            }
          },
          "500" : {
            "description" : "500 response",
            "headers" : {
              "Access-Control-Allow-Origin" : {
                "type" : "string"
              }
            }
          }
        }
      },
      "options" : {
        "consumes" : [ "application/json" ],
        "responses" : {
          "200" : {
            "description" : "200 response",
            "headers" : {
              "Access-Control-Allow-Origin" : {
                "type" : "string"
              },
              "Access-Control-Allow-Methods" : {
                "type" : "string"
              },
              "Access-Control-Allow-Credentials" : {
                "type" : "string"
              },
              "Access-Control-Allow-Headers" : {
                "type" : "string"
              }
            }
          }
        }
      }
    },
    "/usage/update" : {
      "post" : {
        "responses" : {
          "200" : {
            "description" : "200 response",
            "headers" : {
              "Access-Control-Allow-Origin" : {
                "type" : "string"
              },
              "Access-Control-Allow-Methods" : {
                "type" : "string"
              },
              "Access-Control-Allow-Credentials" : {
                "type" : "string"
              },
              "Access-Control-Allow-Headers" : {
                "type" : "string"
              }
            }
          },
          "500" : {
            "description" : "500 response",
            "headers" : {
              "Access-Control-Allow-Origin" : {
                "type" : "string"
              }
            }
          }
        }
      },
      "options" : {
        "consumes" : [ "application/json" ],
        "responses" : {
          "200" : {
            "description" : "200 response",
            "headers" : {
              "Access-Control-Allow-Origin" : {
                "type" : "string"
              },
              "Access-Control-Allow-Methods" : {
                "type" : "string"
              },
              "Access-Control-Allow-Credentials" : {
                "type" : "string"
              },
              "Access-Control-Allow-Headers" : {
                "type" : "string"
              }
            }
          }
        }
      }
    },
    "/usage/{userId}/{engineType}" : {
      "get" : {
        "parameters" : [ {
          "name" : "userId",
          "in" : "path",
          "required" : true,
          "type" : "string"
        }, {
          "name" : "engineType",
          "in" : "path",
          "required" : true,
          "type" : "string"
        } ],
        "responses" : {
          "200" : {
            "description" : "200 response",
            "headers" : {
              "Access-Control-Allow-Origin" : {
                "type" : "string"
              },
              "Access-Control-Allow-Methods" : {
                "type" : "string"
              },
              "Access-Control-Allow-Credentials" : {
                "type" : "string"
              },
              "Access-Control-Allow-Headers" : {
                "type" : "string"
              }
            }
          },
          "500" : {
            "description" : "500 response",
            "headers" : {
              "Access-Control-Allow-Origin" : {
                "type" : "string"
              }
            }
          }
        }
      },
      "post" : {
        "parameters" : [ {
          "name" : "userId",
          "in" : "path",
          "required" : true,
          "type" : "string"
        }, {
          "name" : "engineType",
          "in" : "path",
          "required" : true,
          "type" : "string"
        } ],
        "responses" : {
          "200" : {
            "description" : "200 response",
            "headers" : {
              "Access-Control-Allow-Origin" : {
                "type" : "string"
              },
              "Access-Control-Allow-Methods" : {
                "type" : "string"
              },
              "Access-Control-Allow-Credentials" : {
                "type" : "string"
              },
              "Access-Control-Allow-Headers" : {
                "type" : "string"
              }
            }
          },
          "500" : {
            "description" : "500 response",
            "headers" : {
              "Access-Control-Allow-Origin" : {
                "type" : "string"
              }
            }
          }
        }
      },
      "options" : {
        "consumes" : [ "application/json" ],
        "parameters" : [ {
          "name" : "userId",
          "in" : "path",
          "required" : true,
          "type" : "string"
        }, {
          "name" : "engineType",
          "in" : "path",
          "required" : true,
          "type" : "string"
        } ],
        "responses" : {
          "200" : {
            "description" : "200 response",
            "headers" : {
              "Access-Control-Allow-Origin" : {
                "type" : "string"
              },
              "Access-Control-Allow-Methods" : {
                "type" : "string"
              },
              "Access-Control-Allow-Credentials" : {
                "type" : "string"
              },
              "Access-Control-Allow-Headers" : {
                "type" : "string"
              }
            }
          }
        }
      }
    }
  }
}